nlcmd/__init__.py
nlcmd/cli.py
nlcmd/commands/default.json
nlcmd/config.py
nlcmd/executor.py
nlcmd/parser.py
nlcmd/utils.py
nlcmd/version.py
nlcmd-0.1.0.dist-info/LICENSE
nlcmd-0.1.0.dist-info/METADATA
nlcmd-0.1.0.dist-info/WHEEL
nlcmd-0.1.0.dist-info/entry_points.txt
nlcmd-0.1.0.dist-info/RECORD
