Metadata-Version: 2.3
Name: nlcmd
Version: 0.1.0
Summary: Offline Natural Language Command Runner
License: MIT
Author: Supreme_dev
Requires-Python: >=3.7,<3.15
Classifier: License :: OSI Approved :: MIT License
Classifier: Programming Language :: Python :: 3
Classifier: Programming Language :: Python :: 3.7
Classifier: Programming Language :: Python :: 3.8
Classifier: Programming Language :: Python :: 3.9
Classifier: Programming Language :: Python :: 3.10
Classifier: Programming Language :: Python :: 3.11
Classifier: Programming Language :: Python :: 3.12
Classifier: Programming Language :: Python :: 3.13
Provides-Extra: nlp
Requires-Dist: PyYAML (>=6.0.1,<7.0.0)
Requires-Dist: rapidfuzz (>=3.9.3,<4.0.0)
Requires-Dist: spacy (>=3.7.5,<4.0.0) ; extra == "nlp"
Requires-Dist: typer[all] (>=0.12.3,<0.13.0)
Project-URL: Homepage, https://github.com/Supremedev7/NLC--Natural-language-command
Project-URL: Repository, https://github.com/Supremedev7/NLC--Natural-language-command
